elicitation_server.py
iflow_mcp_geo_joy_mcp_elicitation_example-0.1.0.dist-info/METADATA
iflow_mcp_geo_joy_mcp_elicitation_example-0.1.0.dist-info/WHEEL
iflow_mcp_geo_joy_mcp_elicitation_example-0.1.0.dist-info/entry_points.txt
iflow_mcp_geo_joy_mcp_elicitation_example-0.1.0.dist-info/top_level.txt
iflow_mcp_geo_joy_mcp_elicitation_example-0.1.0.dist-info/RECORD
