Metadata-Version: 2.4
Name: iflow-mcp_geo-joy_mcp-elicitation-example
Version: 0.1.0
Summary: MCP elicitation demo - interactive table booking system
Author-email: Geo Joy <breachguru@gmail.com>
Requires-Python: >=3.11
Requires-Dist: mcp[cli]>=1.9.4
